django_wsgi/__init__.py
django_wsgi/embedded_wsgi.py
django_wsgi/exc.py
django_wsgi/handler.py
django_wsgi/middleware.py
docs/conf.py
tests/dummy_django_project/__init__.py
tests/dummy_django_project/settings.py
tests/dummy_django_project/urls.py
django_wsgi3-1.0.5.dist-info/METADATA
django_wsgi3-1.0.5.dist-info/WHEEL
django_wsgi3-1.0.5.dist-info/top_level.txt
django_wsgi3-1.0.5.dist-info/RECORD
