Metadata-Version: 2.4
Name: django-wsgi3
Version: 1.0.5
Summary: Enhanced WSGI support (for Django 4.2)
Author-email: evermine18 <edgarsanou@gmail.com>
Project-URL: Homepage, https://github.com/evermine18/django-wsgi
Keywords: django,wsgi,webob,web
Classifier: Development Status :: 5 - Production/Stable
Classifier: Environment :: Web Environment
Classifier: Framework :: Django
Classifier: Intended Audience :: Developers
Classifier: License :: OSI Approved :: BSD License
Classifier: Natural Language :: English
Classifier: Operating System :: OS Independent
Classifier: Programming Language :: Python :: 3
Classifier: Programming Language :: Python :: 3.8
Classifier: Programming Language :: Python :: 3.9
Classifier: Programming Language :: Python :: 3.10
Classifier: Programming Language :: Python :: 3.11
Classifier: Programming Language :: Python :: 3.12
Classifier: Topic :: Internet :: WWW/HTTP
Classifier: Topic :: Internet :: WWW/HTTP :: WSGI
Classifier: Topic :: Security
Requires-Python: >=3.8
Requires-Dist: django>=4.2
Requires-Dist: WebOb>=1.5
Requires-Dist: six>=1.10.0
Requires-Dist: setuptools
Provides-Extra: tests
Requires-Dist: coverage; extra == "tests"
Requires-Dist: nose; extra == "tests"
